{
  "name": "CoinGecko",
  "logoURI": "https://static.coingecko.com/s/thumbnail-007177f3eca19695592f0b8b0eabbdae282b54154e1be912285c9034ea6cbaf2.png",
  "keywords": [
    "defi"
  ],
  "timestamp": "2024-10-24T04:00:01.995+00:00",
  "tokens": [
    {
      "chainId": 10241024,
      "address": "0x75dd0e55937947005b91e6c047fdd29d98a5e096",
      "name": "AlienXChain",
      "symbol": "AIX",
      "decimals": 18,
      "logoURI": "https://assets.coingecko.com/coins/images/51011/thumb/aix.jpg?1729738136"
    }
  ],
  "version": {
    "major": 0,
    "minor": 1,
    "patch": 0
  }
}