{
  "name": "CoinGecko",
  "logoURI": "https://static.coingecko.com/s/thumbnail-007177f3eca19695592f0b8b0eabbdae282b54154e1be912285c9034ea6cbaf2.png",
  "keywords": [
    "defi"
  ],
  "timestamp": "2024-12-26T14:00:41.031+00:00",
  "tokens": [
    {
      "chainId": 1234,
      "address": "0xd6070ae98b8069de6b494332d1a1a81b6179d960",
      "name": "Step Bridged WAVAX  Step Network ",
      "symbol": "WAVAX",
      "decimals": 18,
      "logoURI": "https://assets.coingecko.com/coins/images/53093/thumb/step-bridged-wavax-step-network.png?1735220431"
    },
    {
      "chainId": 1234,
      "address": "0x68b2dfc494362aae300f2c401019205d8960226b",
      "name": "KCAL",
      "symbol": "KCAL",
      "decimals": 18,
      "logoURI": "https://assets.coingecko.com/coins/images/27815/thumb/kcal.png?1696526834"
    },
    {
      "chainId": 1234,
      "address": "0xb44a9b6905af7c801311e8f4e76932ee959c663c",
      "name": "Step Bridged WBTC  Step Network ",
      "symbol": "WBTC",
      "decimals": 8,
      "logoURI": "https://assets.coingecko.com/coins/images/39591/thumb/wbtc.png?1723016853"
    },
    {
      "chainId": 1234,
      "address": "0x0bbe45a033aab7a90006c05aa648efd3d2993f9e",
      "name": "PRIMAL",
      "symbol": "PRIMAL",
      "decimals": 18,
      "logoURI": "https://assets.coingecko.com/coins/images/28435/thumb/PRIMAL_ICON_200px.jpg?1696527432"
    },
    {
      "chainId": 1234,
      "address": "0xe3f5a90f9cb311505cd691a46596599aa1a0ad7d",
      "name": "Bridged USDC",
      "symbol": "USDC",
      "decimals": 6,
      "logoURI": "https://assets.coingecko.com/coins/images/35218/thumb/USDC_Icon.png?1707908537"
    },
    {
      "chainId": 1234,
      "address": "0xd67de0e0a0fd7b15dc8348bb9be742f3c5850454",
      "name": "DAO Maker",
      "symbol": "DAO",
      "decimals": 18,
      "logoURI": "https://assets.coingecko.com/coins/images/13915/thumb/4.jpg?1727532864"
    },
    {
      "chainId": 1234,
      "address": "0xb58a9d5920af6ac1a9522b0b10f55df16686d1b6",
      "name": "Step App",
      "symbol": "FITFI",
      "decimals": 18,
      "logoURI": "https://assets.coingecko.com/coins/images/25015/thumb/200x200.png?1701432003"
    },
    {
      "chainId": 1234,
      "address": "0xf390830df829cf22c53c8840554b98eafc5dcbc2",
      "name": "XANA",
      "symbol": "XETA",
      "decimals": 18,
      "logoURI": "https://assets.coingecko.com/coins/images/24379/thumb/XANA_Silver_Logo_%281%29.png?1729504384"
    },
    {
      "chainId": 1234,
      "address": "0xe6801928061cdbe32ac5ad0634427e140efd05f9",
      "name": "XCAD Network",
      "symbol": "XCAD",
      "decimals": 18,
      "logoURI": "https://assets.coingecko.com/coins/images/15857/thumb/xcad_logo.jpg?1707832192"
    }
  ],
  "version": {
    "patch": 3
  }
}