{
  "name": "CoinGecko",
  "logoURI": "https://static.coingecko.com/s/thumbnail-007177f3eca19695592f0b8b0eabbdae282b54154e1be912285c9034ea6cbaf2.png",
  "keywords": [
    "defi"
  ],
  "timestamp": "2025-02-27T08:00:07.004+00:00",
  "tokens": [
    {
      "chainId": 21000000,
      "address": "0xdf0b24095e15044538866576754f3c964e902ee6",
      "name": "Corn Bridged USDC  Corn ",
      "symbol": "USDCE",
      "decimals": 6,
      "logoURI": "https://assets.coingecko.com/coins/images/54568/thumb/usdc.jpg?1740453834"
    },
    {
      "chainId": 21000000,
      "address": "0xda5ddd7270381a7c2717ad10d1c0ecb19e3cdfb2",
      "name": "Wrapped Bitcorn",
      "symbol": "WBTCN",
      "decimals": 18,
      "logoURI": "https://assets.coingecko.com/coins/images/54569/thumb/wbtcn.jpg?1740453965"
    },
    {
      "chainId": 21000000,
      "address": "0x44f49ff0da2498bcb1d3dc7c0f999578f67fd8c6",
      "name": "Corn",
      "symbol": "CORN",
      "decimals": 18,
      "logoURI": "https://assets.coingecko.com/coins/images/54471/thumb/corn.jpg?1739933588"
    },
    {
      "chainId": 21000000,
      "address": "0xecac9c5f704e954931349da37f60e39f515c11c1",
      "name": "Lombard Staked BTC",
      "symbol": "LBTC",
      "decimals": 8,
      "logoURI": "https://assets.coingecko.com/coins/images/39969/thumb/LBTC_Logo.png?1724959872"
    },
    {
      "chainId": 21000000,
      "address": "0x541fd749419ca806a8bc7da8ac23d346f2df8b77",
      "name": "Solv Protocol SolvBTC",
      "symbol": "SOLVBTC",
      "decimals": 18,
      "logoURI": "https://assets.coingecko.com/coins/images/36800/thumb/solvBTC.png?1719810684"
    },
    {
      "chainId": 21000000,
      "address": "0xcc0966d8418d412c599a6421b760a847eb169a8c",
      "name": "Solv Protocol SolvBTC BBN",
      "symbol": "SOLVBTCBBN",
      "decimals": 18,
      "logoURI": "https://assets.coingecko.com/coins/images/39384/thumb/unnamed.png?1721961640"
    }
  ],
  "version": {
    "major": 0,
    "minor": 1,
    "patch": 0
  }
}